print_once/__init__.py
print_once/utils.py
print_once-0.0.2.dist-info/METADATA
print_once-0.0.2.dist-info/WHEEL
print_once-0.0.2.dist-info/top_level.txt
print_once-0.0.2.dist-info/RECORD
