Metadata-Version: 2.1
Name: print-once
Version: 0.0.2
Summary: Allows you to print certain line only once in the loops.
Home-page: https://github.com/juhayna-zh/print-once
Author: Juhayna
Author-email: juhayna@foxmail.com
Classifier: Programming Language :: Python :: 3
Classifier: License :: OSI Approved :: MIT License
Classifier: Operating System :: OS Independent
Requires-Python: >=3.6
